odoo8_addon_web_advanced_search_x2x-8.0.1.0.0.99.dev20-nspkg.pth
odoo_addons/web_advanced_search_x2x/README.rst
odoo_addons/web_advanced_search_x2x/__init__.py
odoo_addons/web_advanced_search_x2x/__openerp__.py
odoo_addons/web_advanced_search_x2x/i18n/ar.po
odoo_addons/web_advanced_search_x2x/i18n/ca.po
odoo_addons/web_advanced_search_x2x/i18n/da.po
odoo_addons/web_advanced_search_x2x/i18n/de.po
odoo_addons/web_advanced_search_x2x/i18n/es.po
odoo_addons/web_advanced_search_x2x/i18n/eu.po
odoo_addons/web_advanced_search_x2x/i18n/fi.po
odoo_addons/web_advanced_search_x2x/i18n/fr.po
odoo_addons/web_advanced_search_x2x/i18n/hr_HR.po
odoo_addons/web_advanced_search_x2x/i18n/it.po
odoo_addons/web_advanced_search_x2x/i18n/nl.po
odoo_addons/web_advanced_search_x2x/i18n/pt_BR.po
odoo_addons/web_advanced_search_x2x/i18n/sl.po
odoo_addons/web_advanced_search_x2x/i18n/tr.po
odoo_addons/web_advanced_search_x2x/i18n/web_advanced_search_x2x.pot
odoo_addons/web_advanced_search_x2x/static/description/icon.png
odoo_addons/web_advanced_search_x2x/static/src/css/web_advanced_search_x2x.css
odoo_addons/web_advanced_search_x2x/static/src/js/web_advanced_search_x2x.js
odoo_addons/web_advanced_search_x2x/static/src/xml/web_advanced_search_x2x.xml
odoo_addons/web_advanced_search_x2x/views/templates.xml
odoo8_addon_web_advanced_search_x2x-8.0.1.0.0.99.dev20.dist-info/METADATA
odoo8_addon_web_advanced_search_x2x-8.0.1.0.0.99.dev20.dist-info/WHEEL
odoo8_addon_web_advanced_search_x2x-8.0.1.0.0.99.dev20.dist-info/namespace_packages.txt
odoo8_addon_web_advanced_search_x2x-8.0.1.0.0.99.dev20.dist-info/top_level.txt
odoo8_addon_web_advanced_search_x2x-8.0.1.0.0.99.dev20.dist-info/RECORD
